{
    "name": "p0tion",
    "identifier": "com.p0tion-Team.p0tion",
    "sourceURL": "https://github.com/p0tion-Team/p0tion-site/raw/main/docs/altstore/p0tionsource.json",
    "apps": [
      {
        "name": "p0tion",
        "bundleIdentifier": "com.p0tion-Team.p0tion",
        "developerName": "p0tion Team",
        "subtitle": "First semi-untethered iOS 14 jailbreak.",
        "version": "0.0.1",
        "versionDate": "2021-2-19",
        "versionDescription": "Works on iOS 12-14.3, arm64e",
        "downloadURL": "https://github.com/p0tion-Team/p0tion-site/raw/main/docs/altstore/p0tion.ipa",
        "localizedDescription": "Supporting iOS Versions: 12-14.3 on arm64e (arm64 eta s0n).\np0tion is the first ever semi-untethered jailbreak working on all devices through iOS 12 - 14.3! It comes with Sileo for a more modern jailbreak feel and will kick off iOS 14's jailbreaking era!",
        "iconURL": "https://github.com/p0tion-Team/p0tion-site/raw/main/docs/img/placeholder.png",
        "tintColor": "D287F4",
        "size": 26463301,
        "beta": true,
        "screenshotURLs": [
          "https://github.com/p0tion-Team/p0tion-site/raw/main/docs/img/p0tion2.png",
        ]
      }
    ],
    "news": [
      {
        "title": "p0tion is now in beta!",
        "identifier": "p0tion-beta-start",
        "caption": "Supports iOS 12-14.3",
        "tintColor": "D287F4",
        "imageURL": "https://github.com/p0tion-Team/p0tion-site/raw/main/docs/img/p0tion2.png",
        "appID": "com.p0tion-Team.p0tion",
        "date": "2021-2-19",
        "notify": true
      },
         {
        "title": "p0tion Repo",
        "identifier": "welcome-to-p0tion-repo",
        "caption": "p0tion is now on AltStore!",
        "tintColor": "D287F4",
        "url": "https://github.com/p0tion-Team/p0tion-site/raw/main/docs/altstore/p0tionsource.json",
        "date": "2021-2-19T12:59:00-07:00",
        "notify": false
      }
    ],
    "userInfo": {}
  }
